doctyper-0.21.1.dist-info/METADATA
doctyper-0.21.1.dist-info/WHEEL
doctyper-0.21.1.dist-info/entry_points.txt
doctyper-0.21.1.dist-info/licenses/LICENSE
doctyper/__init__.py
doctyper/__main__.py
doctyper/_completion_classes.py
doctyper/_completion_shared.py
doctyper/_types.py
doctyper/_typing.py
doctyper/cli.py
doctyper/colors.py
doctyper/completion.py
doctyper/core.py
doctyper/main.py
doctyper/models.py
doctyper/params.py
doctyper/py.typed
doctyper/rich_utils.py
doctyper/testing.py
doctyper/utils.py
doctyper-0.21.1.dist-info/RECORD
