Metadata-Version: 2.4
Name: doctyper
Version: 0.21.1
Summary: Wrapper around Typer using Google-Doc strings for CLI descriptions.
Author-Email: =?utf-8?q?Sebasti=C3=A1n_Ram=C3=ADrez?= <tiangolo@gmail.com>
Maintainer-Email: =?utf-8?q?Tim_H=C3=B6rmann?= <pypi@audivir.de>
License-Expression: MIT
License-File: LICENSE
Classifier: Intended Audience :: Information Technology
Classifier: Intended Audience :: System Administrators
Classifier: Operating System :: OS Independent
Classifier: Programming Language :: Python :: 3
Classifier: Programming Language :: Python
Classifier: Topic :: Software Development :: Libraries :: Application Frameworks
Classifier: Topic :: Software Development :: Libraries :: Python Modules
Classifier: Topic :: Software Development :: Libraries
Classifier: Topic :: Software Development
Classifier: Typing :: Typed
Classifier: Development Status :: 4 - Beta
Classifier: Intended Audience :: Developers
Classifier: Programming Language :: Python :: 3 :: Only
Classifier: Programming Language :: Python :: 3.9
Classifier: Programming Language :: Python :: 3.10
Classifier: Programming Language :: Python :: 3.11
Classifier: Programming Language :: Python :: 3.12
Classifier: Programming Language :: Python :: 3.13
Classifier: Programming Language :: Python :: 3.14
Project-URL: Homepage, https://github.com/audivir/doctyper
Project-URL: Documentation, https://typer.tiangolo.com
Project-URL: Repository, https://github.com/audivir/doctyper
Project-URL: Issues, https://github.com/audivir/doctyper/issues
Requires-Python: >=3.9
Requires-Dist: click>=8.0.0
Requires-Dist: docstring-parser
Requires-Dist: eval-type-backport
Requires-Dist: typing-extensions>=3.7.4.3
Requires-Dist: shellingham>=1.3.0
Requires-Dist: rich>=10.11.0
